aiida_gui_workgraph/__init__.py
aiida_gui_workgraph/workgraph.py
aiida_gui_workgraph/static/workgraph.esm.js
aiida_gui_workgraph-0.1.3.dist-info/licenses/LICENSE
aiida_gui_workgraph-0.1.3.dist-info/METADATA
aiida_gui_workgraph-0.1.3.dist-info/WHEEL
aiida_gui_workgraph-0.1.3.dist-info/entry_points.txt
aiida_gui_workgraph-0.1.3.dist-info/top_level.txt
aiida_gui_workgraph-0.1.3.dist-info/RECORD
