Metadata-Version: 2.4
Name: aiida_gui_workgraph
Version: 0.1.3
Summary: Design flexible node-based workflow for AiiDA calculation.
Author-email: Xing Wang <xingwang1991@gmail.com>
License: MIT License
Project-URL: Documentation, https://aiida-gui-workgraph.readthedocs.io
Project-URL: Source, https://github.com/aiidateam/aiida-gui-workgraph
Classifier: Development Status :: 1 - Planning
Classifier: Framework :: AiiDA
Classifier: License :: OSI Approved :: MIT License
Classifier: Operating System :: POSIX :: Linux
Classifier: Operating System :: MacOS :: MacOS X
Classifier: Programming Language :: Python
Classifier: Programming Language :: Python :: 3.9
Classifier: Programming Language :: Python :: 3.10
Classifier: Programming Language :: Python :: 3.11
Classifier: Programming Language :: Python :: 3.12
Classifier: Topic :: Scientific/Engineering
License-File: LICENSE
Requires-Dist: aiida-gui
Provides-Extra: pre-commit
Requires-Dist: pre-commit~=2.2; extra == "pre-commit"
Requires-Dist: pylint~=2.17.4; extra == "pre-commit"
Dynamic: license-file
